streamlit_patch/__init__.py
streamlit_patch/calculator.py
streamlit_patch/db_connector.py
streamlit_patch/markdown_handler.py
streamlit_patch/rec_container.py
streamlit_patch/report_summary.py
streamlit_patch-0.0.31.dist-info/METADATA
streamlit_patch-0.0.31.dist-info/WHEEL
streamlit_patch-0.0.31.dist-info/top_level.txt
streamlit_patch-0.0.31.dist-info/RECORD
