Metadata-Version: 2.1
Name: streamlit_patch
Version: 0.0.31
Summary: A streamlit patch for markdown render
Home-page: https://github.com/qixiaojian310/streamlit_patch
Author: qixiaojian310
Author-email: qixiaojian00310@163.com
License: MIT Licence
Keywords: pip,streamlit_patch
Platform: any
Requires-Dist: streamlit==1.40.1
Requires-Dist: streamlit-echarts==0.4.0
Requires-Dist: streamlit-float==0.3.5
Requires-Dist: streamlit-js-eval==0.1.7
Requires-Dist: pandas<=2.0.3
Requires-Dist: numpy<=1.24.4
